README.md
setup.py
turbine/__init__.py
turbine/engine.py
turbine/worker.py
turbine.egg-info/PKG-INFO
turbine.egg-info/SOURCES.txt
turbine.egg-info/dependency_links.txt
turbine.egg-info/requires.txt
turbine.egg-info/top_level.txt