Metadata-Version: 2.1
Name: turbine
Version: 1.3.0
Summary: A Python 3 tool to harness the google cloud to run shell scripts
Home-page: https://github.com/Kasekopf/Turbine
Author: Jeffrey Dudek
Author-email: jeffreydudek@gmail.com
License: MIT
Platform: Posix; MacOS X; Windows
Classifier: Programming Language :: Python :: 3
Classifier: License :: OSI Approved :: MIT License
Classifier: Operating System :: OS Independent
Requires-Python: >=3.6
